catplotlib
