Metadata-Version: 2.1
Name: catplotlib
Version: 1.0.1
Summary: Matplotlib, but for cats.
Home-page: https://github.com/achabotl/catplotlib
Author: Alexandre Chabot-Leclerc
Author-email: accounts.github@alex.alexchabot.net
License: MIT license
Keywords: catplotlib
Classifier: Intended Audience :: Developers
Classifier: License :: OSI Approved :: MIT License
Classifier: Natural Language :: English
Classifier: Programming Language :: Python :: 3
Classifier: Programming Language :: Python :: 3.6
Classifier: Programming Language :: Python :: 3.7
Classifier: Programming Language :: Python :: 3.8
Requires-Python: >=3.6
License-File: LICENSE
